[{"model": "staff.position", "pk": 1, "fields": {"name": "Президент Международного университета SILKWAY", "slug": "prezident-mezhdunarodnogo-universiteta-silkway"}}, {"model": "staff.position", "pk": 2, "fields": {"name": "Ректор", "slug": "rektor"}}, {"model": "staff.position", "pk": 3, "fields": {"name": "Проректор по цифровизации", "slug": "prorektor-po-cifrovizacii"}}, {"model": "staff.position", "pk": 4, "fields": {"name": "Проректор по стратегическому развитию", "slug": "prorektor-po-strategicheskomu-razvitiyu"}}, {"model": "staff.position", "pk": 5, "fields": {"name": "Доктор Технических Наук", "slug": "doktor-tehnicheskih-nauk"}}, {"model": "staff.position", "pk": 6, "fields": {"name": "PhD", "slug": "phd"}}, {"model": "staff.position", "pk": 7, "fields": {"name": "Заведующий кафедры, к.п.н., и.о. доцента", "slug": "zaveduyushij-kafedry-kpn-io-docenta"}}, {"model": "staff.position", "pk": 8, "fields": {"name": "к.п.н., профессор", "slug": "kpn-professor"}}, {"model": "staff.staffcat", "pk": 1, "fields": {"name": "Международный экспертный Совет", "slug": "mezhdunarodnyj-ekspertnyj-sovet"}}, {"model": "staff.staffcat", "pk": 2, "fields": {"name": "Попечительский Совет", "slug": "popechitelskij-sovet"}}, {"model": "staff.staffcat", "pk": 3, "fields": {"name": "Руководство университета", "slug": "rukovodstvo-universiteta"}}, {"model": "staff.staffcat", "pk": 4, "fields": {"name": "Препователи", "slug": "prepovateli"}}, {"model": "staff.staff", "pk": 2, "fields": {"name": "Iring Wasser", "slug": "iring-wasser", "img": "Staff/Posters/2.png", "position": 6, "staffCat": 1, "department": null, "educationalPrograms": null, "email": null, "adress": "Германия", "phone": null, "about": "Генеральный директор Германского аккредитационного агентства в области естественных наук и информационных технологий ASIIN"}}, {"model": "staff.staff", "pk": 3, "fields": {"name": "Yu Tao", "slug": "yu-tao", "img": "Staff/Posters/3.png", "position": 5, "staffCat": 1, "department": null, "educationalPrograms": null, "email": null, "adress": "КНР", "phone": null, "about": "Президент «Шанхайского политехнического университета»"}}, {"model": "staff.staff", "pk": 4, "fields": {"name": "Fakhru'l-Razi Ahmadun", "slug": "fakhrul-razi-ahmadun", "img": "Staff/Posters/4.png", "position": 5, "staffCat": 1, "department": null, "educationalPrograms": null, "email": null, "adress": "Малайзия", "phone": null, "about": "Директор Исследовательского центра гуманитарной помощи и ликвидации последствий стихийных бедствий (HADR) Университета Национальной безопасности"}}, {"model": "staff.staff", "pk": 5, "fields": {"name": "Robert Ferrer Miquel", "slug": "robert-ferrer-miquel", "img": "Staff/Posters/5.png", "position": 6, "staffCat": 1, "department": null, "educationalPrograms": null, "email": null, "adress": "Испания", "phone": null, "about": "Руководитель международного офиса Университета Барселоны"}}, {"model": "staff.staff", "pk": 6, "fields": {"name": "Amir Said Shirani", "slug": "amir-said-shirani", "img": "Staff/Posters/6.png", "position": 6, "staffCat": 1, "department": null, "educationalPrograms": null, "email": null, "adress": "Иран, Тегеран", "phone": null, "about": "Директор Международного учебного бюро по сотрудничеству в университете Шахида Бехешти"}}, {"model": "staff.staff", "pk": 7, "fields": {"name": "Исманова Рабига Жолдасовна", "slug": "ismanova-rabiga-zholdasovna", "img": "Staff/Posters/1_D3LewSv.png", "position": 7, "staffCat": 4, "department": 3, "educationalPrograms": null, "email": "ismanova-rabiga-zholdasovna@gmail.com", "adress": "Тажибаев 28", "phone": "87059943864", "about": "описание о Исманова Рабига Жолдасовна"}}]